polyphase/__init__.py
polyphase/channelizer.py
polyphase-0.1.2.dist-info/LICENSE
polyphase-0.1.2.dist-info/WHEEL
polyphase-0.1.2.dist-info/METADATA
polyphase-0.1.2.dist-info/RECORD
